odoo/addons/stock_picking_batch_back2draft/README.rst
odoo/addons/stock_picking_batch_back2draft/__init__.py
odoo/addons/stock_picking_batch_back2draft/__manifest__.py
odoo/addons/stock_picking_batch_back2draft/i18n/stock_picking_batch_back2draft.pot
odoo/addons/stock_picking_batch_back2draft/models/__init__.py
odoo/addons/stock_picking_batch_back2draft/models/stock_picking_batch.py
odoo/addons/stock_picking_batch_back2draft/readme/CONTRIBUTORS.rst
odoo/addons/stock_picking_batch_back2draft/readme/DESCRIPTION.rst
odoo/addons/stock_picking_batch_back2draft/readme/USAGE.rst
odoo/addons/stock_picking_batch_back2draft/static/description/icon.png
odoo/addons/stock_picking_batch_back2draft/static/description/index.html
odoo/addons/stock_picking_batch_back2draft/views/stock_picking_batch_view.xml
odoo12_addon_stock_picking_batch_back2draft-12.0.1.0.0.99.dev3.dist-info/METADATA
odoo12_addon_stock_picking_batch_back2draft-12.0.1.0.0.99.dev3.dist-info/WHEEL
odoo12_addon_stock_picking_batch_back2draft-12.0.1.0.0.99.dev3.dist-info/top_level.txt
odoo12_addon_stock_picking_batch_back2draft-12.0.1.0.0.99.dev3.dist-info/RECORD
